{
  "project_info": {
    "project_number": "27729340317",
    "firebase_url": "https://sapper-sveltefire-tailwindcss.firebaseio.com",
    "project_id": "sapper-sveltefire-tailwindcss",
    "storage_bucket": "sapper-sveltefire-tailwindcss.appspot.com"
  },
  "client": [
    {
      "client_info": {
        "mobilesdk_app_id": "1:27729340317:android:e34ccd0f2529b92eeef174",
        "android_client_info": {
          "package_name": "com.example.flutter_firebase"
        }
      },
      "oauth_client": [
        {
          "client_id": "27729340317-hmnq0q7tbm269nli8vg45fqk6fiuc9qi.apps.googleusercontent.com",
          "client_type": 1,
          "android_info": {
            "package_name": "com.example.flutter_firebase",
            "certificate_hash": "add7fbe10c6aa60c7400ea5deb9e51413bce4365"
          }
        },
        {
          "client_id": "27729340317-3hvq26i5svc3ojjlb95k4spe3ve7vfhs.apps.googleusercontent.com",
          "client_type": 3
        }
      ],
      "api_key": [
        {
          "current_key": "AIzaSyB03x17QQ1vtDpmissz-OwQ_7cR8M3MEhQ"
        }
      ],
      "services": {
        "appinvite_service": {
          "other_platform_oauth_client": [
            {
              "client_id": "27729340317-3hvq26i5svc3ojjlb95k4spe3ve7vfhs.apps.googleusercontent.com",
              "client_type": 3
            }
          ]
        }
      }
    }
  ],
  "configuration_version": "1"
}